LICENSE
password_policy/__init__.py
password_policy/calculator.py
password_policy/data.py
password_policy/validate.py
password_policy-0.2.0.dist-info/LICENSE
password_policy-0.2.0.dist-info/WHEEL
password_policy-0.2.0.dist-info/METADATA
password_policy-0.2.0.dist-info/RECORD
