Metadata-Version: 2.1
Name: password-policy
Version: 0.2.0
Summary: Library for representing password policies in a machine-readable format. Also supports validating passwords against policies and for estimating the strength of passwords created under a given policy.
Home-page: https://bitbucket.org/user-lab/password-policy/src/master/
License: MIT
Author: Scott Ruoti
Author-email: ruoti@utk.edu
Requires-Python: >=3.6.1
Classifier: License :: OSI Approved :: MIT License
Classifier: Programming Language :: Python :: 3
Classifier: Programming Language :: Python :: 3.10
Classifier: Programming Language :: Python :: 3.7
Classifier: Programming Language :: Python :: 3.8
Classifier: Programming Language :: Python :: 3.9
Requires-Dist: pydantic (>=1.9,<1.10)
Project-URL: Repository, https://bitbucket.org/user-lab/password-policy/src/master/
